markdown_equations_fixer/__init__.py
markdown_equations_fixer/cli.py
markdown_equations_fixer-1.1.5.dist-info/licenses/LICENSE
markdown_equations_fixer-1.1.5.dist-info/METADATA
markdown_equations_fixer-1.1.5.dist-info/WHEEL
markdown_equations_fixer-1.1.5.dist-info/entry_points.txt
markdown_equations_fixer-1.1.5.dist-info/top_level.txt
markdown_equations_fixer-1.1.5.dist-info/RECORD
