Metadata-Version: 2.4
Name: markdown-equations-fixer
Version: 1.1.5
Summary: A CLI tool to fix mathematical equations in markdown files and convert between formats
Home-page: https://github.com/dynstat/markdown-equations-fixer
Author: Vivek Singh
Author-email: vs15vivek@gmail.com
Classifier: Programming Language :: Python :: 3
Classifier: License :: OSI Approved :: MIT License
Classifier: Operating System :: OS Independent
Requires-Python: >=3.7
License-File: LICENSE
Requires-Dist: click>=8.0.0
Requires-Dist: rich>=10.0.0
Requires-Dist: pypandoc
Dynamic: author
Dynamic: author-email
Dynamic: classifier
Dynamic: description
Dynamic: description-content-type
Dynamic: home-page
Dynamic: license-file
Dynamic: requires-dist
Dynamic: requires-python
Dynamic: summary
